{"452737276812984330": {"Wallet": 0.0, "Bank": 30693, "bag": [{"item": "watch", "amount": 0}, {"item": "laptop", "amount": 0}, {"item": "pc", "amount": 0}]}, "556801303595188227": {"Wallet": 0, "Bank": 129}, "748881940425342996": {"Wallet": 161, "Bank": 275}, "503130444427165707": {"Wallet": 398, "Bank": 0}, "705659641928876084": {"Wallet": 37, "Bank": 0, "bag": [{"item": "laptop", "amount": 1}]}, "795861753627672607": {"Wallet": 0, "Bank": 10204020530, "bag": [{"item": "watch", "amount": 48584}, {"item": "laptop", "amount": 6848}, {"item": "PC", "amount": 56000}, {"item": "Nitro", "amount": 0}, {"item": "Fog perfume", "amount": 998766}]}, "636507125924757504": {"Wallet": 0, "Bank": 0}, "596355578994098177": {"Wallet": 0, "Bank": 0}, "617609010002132992": {"Wallet": 1000, "Bank": 31695, "bag": [{"item": "pc", "amount": 1}]}, "270904126974590976": {"Wallet": 100, "Bank": 0}}